ressenter/__init__.py
ressenter/cli.py
ressenter/output.py
ressenter/util.py
ressenter/capabilities/__init__.py
ressenter/capabilities/comments.py
ressenter/capabilities/trending.py
ressenter/capabilities/url.py
ressenter/capabilities/user.py
ressenter-0.0.11.dist-info/LICENSE
ressenter-0.0.11.dist-info/METADATA
ressenter-0.0.11.dist-info/WHEEL
ressenter-0.0.11.dist-info/entry_points.txt
ressenter-0.0.11.dist-info/top_level.txt
ressenter-0.0.11.dist-info/RECORD
