Metadata-Version: 2.1
Name: ressenter
Version: 0.0.11
Summary: Toolkit for Dissenter
Home-page: https://github.com/stanfordio/ressenter
Author-email: mccain@stanford.edu
License: Apache License 2.0
Platform: UNKNOWN
Classifier: License :: OSI Approved :: Apache Software License
Classifier: Programming Language :: Python :: 3
Classifier: Programming Language :: Python :: 3.8
Requires-Python: >=3.8
Requires-Dist: beautifulsoup4
Requires-Dist: requests
Requires-Dist: click
Requires-Dist: unicodecsv
Requires-Dist: dateparser
